README.md
setup.py
cproc/__init__.py
cproc/wrapper.py
cproc.egg-info/PKG-INFO
cproc.egg-info/SOURCES.txt
cproc.egg-info/dependency_links.txt
cproc.egg-info/requires.txt
cproc.egg-info/top_level.txt
scripts/cproc
scripts/rproc