Metadata-Version: 2.1
Name: cproc
Version: 0.1.5
Summary: A small tool to capture the environment of a running process
Home-page: https://bitbucket.org/jakobsg/cproc
Author: Jakob Simon-Gaarde
Author-email: jakobsg@simon-gaarde.dk
License: UNKNOWN
Platform: UNKNOWN
Classifier: Programming Language :: Python :: 2
Classifier: Programming Language :: Python :: 3
Classifier: License :: OSI Approved :: MIT License
Classifier: Operating System :: OS Independent
Requires-Python: >=2.6
